{
  "question": {
    "tags": [
      "java",
      "text",
      "colors"
    ],
    "owner": {
      "account_id": 372412,
      "reputation": 5015,
      "user_id": 721443,
      "user_type": "registered",
      "profile_image": "https://www.gravatar.com/avatar/8ba3d8cac1a3c21255ce06cbe46fd16a?s=256&d=identicon&r=PG",
      "display_name": "Taranath Datta",
      "link": "https://stackoverflow.com/users/721443/taranath-datta"
    },
    "is_answered": true,
    "view_count": 694277,
    "protected_date": 1513011255,
    "answer_count": 17,
    "score": 500,
    "last_activity_date": 1702880489,
    "creation_date": 1303537973,
    "last_edit_date": 1500869195,
    "question_id": 5762491,
    "content_license": "CC BY-SA 3.0",
    "link": "https://stackoverflow.com/questions/5762491/how-to-print-color-in-console-using-system-out-println",
    "title": "How to print color in console using System.out.println?",
    "body": "<p>How can I print color in console? I want to show data in colors when the processor sends data and in different colors when it receives data.</p>\n"
  },
  "answers": [
    {
      "owner": {
        "account_id": 2800537,
        "reputation": 506,
        "user_id": 2408863,
        "user_type": "registered",
        "profile_image": "https://www.gravatar.com/avatar/fc594b0407c6c9357a7d04ef6530ca0d?s=256&d=identicon&r=PG",
        "display_name": "tonnoz",
        "link": "https://stackoverflow.com/users/2408863/tonnoz"
      },
      "is_accepted": false,
      "score": -2,
      "last_activity_date": 1702880489,
      "creation_date": 1702880489,
      "answer_id": 77677280,
      "question_id": 5762491,
      "content_license": "CC BY-SA 4.0",
      "body": "<p>For Kotlin people:</p>\n<pre class=\"lang-kotlin prettyprint-override\"><code>fun Any.bold(color: String = &quot;&quot;): String = style(&quot;$color;1&quot;)\nfun Any.underline(color: String = &quot;&quot;): String = style(&quot;$color;4&quot;)\nfun Any.style(color: String): String { return &quot;\\u001B[${color}m$this\\u001B[0m&quot; }\n\nfun Any.colored(fgCol:String, bgCol: String, bold: Boolean = false): String {\n  return if(bold) &quot;\\u001B[${fgCol};${bgCol};1m$this\\u001B[0m&quot;\n  else &quot;\\u001B[${fgCol};${bgCol}m$this\\u001B[0m&quot;\n}\n</code></pre>\n<p>Then use it with these constants:</p>\n<pre><code>Text Colors\n     30     BLACK\n     31       RED\n     32     GREEN\n     33    YELLOW\n     34      BLUE\n     35   MAGENTA\n     36      CYAN\n     37     WHITE\n \nBackground\n     40    BLACK\n     41      RED\n     42    GREEN\n     43   YELLOW\n     44     BLUE\n     45  MAGENTA\n     46     CYAN\n     47    WHITE\n \nHigh Intensity Text\n     90     BLACK\n     91       RED\n     92     GREEN\n     93    YELLOW\n     94      BLUE\n     95   MAGENTA\n     96      CYAN\n     97     WHITE\n\n\nHigh Intensity backgrounds\n     100      BLACK\n     101        RED\n     102     GREEN\n     103    YELLOW\n     104      BLUE\n     105   MAGENTA\n     106      CYAN\n     107     WHITE\n</code></pre>\n<p>Usage:</p>\n<pre class=\"lang-kotlin prettyprint-override\"><code>println(&quot;yourString&quot;.bold(&quot;33&quot;)) // will print a yellow bold text\n</code></pre>\n<p>To reset the color of the terminal call the style fun with <code>&quot;&quot;</code> as color.</p>\n<p>Enjoy!</p>\n"
    },
    {
      "owner": {
        "account_id": 27849611,
        "reputation": 26,
        "user_id": 21264381,
        "user_type": "registered",
        "profile_image": "https://www.gravatar.com/avatar/1a3d38cbc0f8f0767ab4123f8853b95c?s=256&d=identicon&r=PG",
        "display_name": "Michael_123",
        "link": "https://stackoverflow.com/users/21264381/michael-123"
      },
      "is_accepted": false,
      "score": 1,
      "last_activity_date": 1699523041,
      "creation_date": 1699523041,
      "answer_id": 77452043,
      "question_id": 5762491,
      "content_license": "CC BY-SA 4.0",
      "body": "<p>Good to konw, e.g. I use Eclipse and the <code>\\u033</code>-Prefix-Code does not work. Just use <code>\\u001B</code> or <code>\\u001b</code> to make it work.</p>\n<p>This was shown in the first post but then people switch to &quot;033&quot; without a comment about that their solution ist an alterative way.\nBut thank all af you who posted - that will help!</p>\n<p>Maybe it is useful for you :)</p>\n"
    }
  ],
  "question_comments": [
    {
      "owner": {
        "account_id": 5607464,
        "reputation": 1825,
        "user_id": 4441477,
        "user_type": "registered",
        "profile_image": "https://www.gravatar.com/avatar/f92182839b265074948295c7bf513548?s=256&d=identicon&r=PG",
        "display_name": "jw_",
        "link": "https://stackoverflow.com/users/4441477/jw"
      },
      "edited": false,
      "score": 2,
      "creation_date": 1568597791,
      "post_id": 5762491,
      "comment_id": 102311667,
      "content_license": "CC BY-SA 4.0"
    }
  ],
  "answer_comments": {
    "77677280": [],
    "77452043": []
  }
}