{
  "question": {
    "tags": [
      "java",
      "apache-camel",
      "soa",
      "enterprise-integration"
    ],
    "owner": {
      "account_id": 891545,
      "reputation": 18627,
      "user_id": 929694,
      "user_type": "registered",
      "accept_rate": 76,
      "profile_image": "https://i.sstatic.net/pBrhW.jpg?s=256",
      "display_name": "Myy",
      "link": "https://stackoverflow.com/users/929694/myy"
    },
    "is_answered": true,
    "view_count": 705844,
    "protected_date": 1340020091,
    "accepted_answer_id": 11540451,
    "answer_count": 21,
    "score": 1654,
    "last_activity_date": 1736893393,
    "creation_date": 1326421938,
    "last_edit_date": 1453994732,
    "question_id": 8845186,
    "content_license": "CC BY-SA 3.0",
    "link": "https://stackoverflow.com/questions/8845186/what-exactly-is-apache-camel",
    "title": "What exactly is Apache Camel?",
    "body": "<p>I don't understand what exactly <a href=\"http://camel.apache.org/index.html\" rel=\"noreferrer\">Camel</a> does.</p>\n\n<p>If you could give in 101 words an introduction to Camel:</p>\n\n<ul>\n<li>What exactly is it? </li>\n<li>How does it interact with an application written in Java? </li>\n<li>Is it something that goes together with the server? </li>\n<li>Is it an independent program? </li>\n</ul>\n\n<p><strong>Please explain what Camel is.</strong></p>\n"
  },
  "answers": [],
  "question_comments": [],
  "answer_comments": {}
}