{
  "question": {
    "tags": [
      "java",
      "android",
      "react-native",
      "gradle"
    ],
    "owner": {
      "account_id": 22702283,
      "reputation": 105,
      "user_id": 16869520,
      "user_type": "registered",
      "profile_image": "https://lh3.googleusercontent.com/a-/AOh14GhAg3ivpOkte4fpmtzE4e84-Jj1wV4gN0fe7bOE=k-s256",
      "display_name": "Prithvi Emmanuel Machado",
      "link": "https://stackoverflow.com/users/16869520/prithvi-emmanuel-machado"
    },
    "is_answered": true,
    "view_count": 4957,
    "accepted_answer_id": 78065172,
    "answer_count": 2,
    "score": 3,
    "last_activity_date": 1714028916,
    "creation_date": 1708242172,
    "question_id": 78014960,
    "content_license": "CC BY-SA 4.0",
    "link": "https://stackoverflow.com/questions/78014960/react-native-gradle-build-error-temporary-workspace-copy-error",
    "title": "React native gradle build error -&gt; temporary workspace copy error",
    "body": "<p>I am currently trying to test out google login with expo, and I am facing the following error when using <code>expo run:android</code></p>\n<pre><code>A problem occurred configuring project ':gradle-plugin'.\n Multiple build operations failed.\n  Could not move temporary workspace (C:\\Users\\&lt;username&gt;\\.gradle\\caches\\transforms-4\\04b2391c437efaa204e156de4d548a2b-cda26d44-b981-4798-8f46-71509d888824) to immutable location (C:\\Users\\&lt;username&gt;\\.gradle\\caches\\transforms-4\\04b2391c437efaa204e156de4d548a2b)\n</code></pre>\n<p>there are multiple such failed move operations. I tried stopping gradle and deleting the cache, it still did not work. I have tried running the command as admin still no go. I ran <code>gradlew --stacktrace</code> this is what I got but cannot understand what that means</p>\n<pre><code>     * Exception is:\n    org.gradle.api.ProjectConfigurationException: A problem occurred configuring project ':gradle-plugin'.\n    at org.gradle.configuration.project.LifecycleProjectEvaluator.wrapException(LifecycleProjectEvaluator.java:84)\n    at org.gradle.configuration.project.LifecycleProjectEvaluator.addConfigurationFailure(LifecycleProjectEvaluator.java:77)\n    at org.gradle.configuration.project.LifecycleProjectEvaluator.access$500(LifecycleProjectEvaluator.java:55)\n    at org.gradle.configuration.project.LifecycleProjectEvaluator$EvaluateProject.lambda$run$0(LifecycleProjectEvaluator.java:111)\n    at org.gradle.api.internal.project.DefaultProjectStateRegistry$ProjectStateImpl.lambda$applyToMutableState$1(DefaultProjectStateRegistry.java:407)\n    at org.gradle.api.internal.project.DefaultProjectStateRegistry$ProjectStateImpl.lambda$fromMutableState$2(DefaultProjectStateRegistry.java:430)\n    at org.gradle.internal.work.DefaultWorkerLeaseService.withReplacedLocks(DefaultWorkerLeaseService.java:360)\n    at org.gradle.api.internal.project.DefaultProjectStateRegistry$ProjectStateImpl.fromMutableState(DefaultProjectStateRegistry.java:430)\n    at org.gradle.api.internal.project.DefaultProjectStateRegistry$ProjectStateImpl.applyToMutableState(DefaultProjectStateRegistry.java:406)\n    at org.gradle.configuration.project.LifecycleProjectEvaluator$EvaluateProject.run(LifecycleProjectEvaluator.java:100)\n    at org.gradle.internal.operations.DefaultBuildOperationRunner$1.execute(DefaultBuildOperationRunner.java:29)\n    at org.gradle.internal.operations.DefaultBuildOperationRunner$1.execute(DefaultBuildOperationRunner.java:26)\n    at org.gradle.internal.operations.DefaultBuildOperationRunner$2.execute(DefaultBuildOperationRunner.java:66)\n    at org.gradle.internal.operations.DefaultBuildOperationRunner$2.execute(DefaultBuildOperationRunner.java:59)\n    at org.gradle.internal.operations.DefaultBuildOperationRunner.execute(DefaultBuildOperationRunner.java:157)\n    at org.gradle.internal.operations.DefaultBuildOperationRunner.execute(DefaultBuildOperationRunner.java:59)\n</code></pre>\n<p>I have not made any changes to the config files except the following</p>\n<ul>\n<li>/android/gradle/wrapper/gradle-wrapper.properties -&gt; distributionUrl=https://services.gradle.org/distributions/gradle-8.6-all.zip -&gt; was 8.0.1</li>\n<li>/android/build.gradle -&gt; classpath('com.android.tools.build:gradle:8.6') -&gt; was 7.4.2</li>\n</ul>\n<p>I am at a dead end and could use some help. Any help is appreciated. I am using gradle version 8.6-all and Java vesion 21.0.2</p>\n"
  },
  "answers": [],
  "question_comments": [],
  "answer_comments": {}
}