{
  "question": {
    "tags": [
      "java",
      "android"
    ],
    "owner": {
      "account_id": 1210913,
      "reputation": 7825,
      "user_id": 1179459,
      "user_type": "registered",
      "accept_rate": 60,
      "profile_image": "https://i.sstatic.net/t3bBj.png?s=256",
      "display_name": "mahen3d",
      "link": "https://stackoverflow.com/users/1179459/mahen3d"
    },
    "is_answered": true,
    "view_count": 3421,
    "answer_count": 2,
    "score": -2,
    "last_activity_date": 1721832162,
    "creation_date": 1712621232,
    "question_id": 78295557,
    "content_license": "CC BY-SA 4.0",
    "link": "https://stackoverflow.com/questions/78295557/android-api-34-security-exception-one-of-receiver-exported-or-receiver-not-exp",
    "title": "Android API 34 Security Exception - One of RECEIVER_EXPORTED or RECEIVER_NOT_EXPORTED should be specified",
    "body": "<p>When the App runs in Android API 34, App crash with below error, but in API 33 it works fine, I tried many things including adding export=true to Android Manifest but failed to get it working any idea on this ?</p>\n<p><strong>java.lang.RuntimeException: Unable to resume activity {com.npc.marry/com.xxx.ui.login.LoginActivity}: java.lang.SecurityException: com.xxx: One of RECEIVER_EXPORTED or RECEIVER_NOT_EXPORTED should be specified when a receiver isn't being registered exclusively for system broadcasts</strong></p>\n<p>AndroidManifest is like</p>\n<pre><code> &lt;activity\n            android:name=&quot;.ui.login.LoginActivity&quot;\n            android:screenOrientation=&quot;portrait&quot;\n            android:exported=&quot;false&quot; /&gt;\n</code></pre>\n<hr />\n<pre><code>public class LoginActivity extends BaseActivity implements LoginView {\n\n//google sign in code\nprivate static final int RC_SIGN_IN = 9001;\n@NotEmpty\n@BindView(R.id.edtUsername)\nBlackEditText edtUsernamne;\n\n@Password(min = 4)\n@BindView(R.id.edtPassword)\nBlackEditText edtPassword;\n\n@BindView(R.id.btnLogin)\nFancyButton btnLogin;\n\nValidator validator;\nLoginPresenter loginPresenter;\n\n\nprivate final BroadcastReceiver mReceiver = new BroadcastReceiver() {\n    @Override\n    public void onReceive(Context context, Intent intent) {\n        boolean result = intent.getBooleanExtra(&quot;result&quot;, false);\n        if (result) {\n            startActivity(MainActivity.class, null, true);\n        } else {\n            Toast.makeText(LoginActivity.this, &quot;Can not register your device&quot;, Toast.LENGTH_SHORT).show();\n        }\n    }\n};\n\n@Override\nprotected void onCreate(Bundle savedInstanceState) {\n    super.onCreate(savedInstanceState);\n    setContentView(R.layout.activity_login);\n\n    validator = new Validator(this);\n    validator.setValidationListener(this);\n    loginPresenter = new LoginPresenter(this, this, compositeSubscription);\n}\n\n@Override\nprotected void onResume() {\n    super.onResume();\n    LoginActivity.this.registerReceiver(mReceiver, new IntentFilter(&quot;com.result.notification&quot;));\n}\n\n@Override\nprotected void onPause() {\n    super.onPause();\n    LoginActivity.this.unregisterReceiver(mReceiver);\n}\n...\n</code></pre>\n<p>}</p>\n"
  },
  "answers": [],
  "question_comments": [],
  "answer_comments": {}
}