{
  "question": {
    "tags": [
      "java",
      "spring-boot",
      "aws-sdk",
      "amazon-sqs",
      "spring-cloud-aws"
    ],
    "owner": {
      "account_id": 3273973,
      "reputation": 6117,
      "user_id": 2756574,
      "user_type": "registered",
      "accept_rate": 89,
      "profile_image": "https://i.sstatic.net/Jfwkl6k2.png?s=256",
      "display_name": "Sebastian",
      "link": "https://stackoverflow.com/users/2756574/sebastian"
    },
    "is_answered": true,
    "view_count": 341,
    "accepted_answer_id": 78389365,
    "answer_count": 1,
    "score": 0,
    "last_activity_date": 1739830461,
    "creation_date": 1714117660,
    "last_edit_date": 1714118067,
    "question_id": 78388965,
    "content_license": "CC BY-SA 4.0",
    "link": "https://stackoverflow.com/questions/78388965/java-class-for-aws-s3-to-sqs-event-in-the-sdk",
    "title": "Java class for AWS S3 to SQS Event in the SDK",
    "body": "<p>I wonder if there are any ready-to-use java classes in the aws-sdk or spring-cloud-aws for standard SQS events like S3 &quot;ObjectCreated:Put&quot; or if I need to create them on my own.</p>\n<p>I didn't find any and all examples seem to use very simple event bodies but maybe I'm blind.</p>\n<p>Example for what I'm talking about:</p>\n<pre><code>{\n  &quot;Records&quot;: [\n    {\n      &quot;eventVersion&quot;: &quot;2.1&quot;,\n      &quot;eventSource&quot;: &quot;aws:s3&quot;,\n      &quot;awsRegion&quot;: &quot;eu-central-1&quot;,\n      &quot;eventTime&quot;: &quot;2024-04-19T08:43:56.425Z&quot;,\n      &quot;eventName&quot;: &quot;ObjectCreated:Put&quot;,\n      &quot;userIdentity&quot;: {\n        &quot;principalId&quot;: &quot;AWS:AKJSDGHJKAHSDKJAASD&quot;\n      },\n      &quot;requestParameters&quot;: {\n        &quot;sourceIPAddress&quot;: &quot;92.79.75.114&quot;\n      },\n      &quot;responseElements&quot;: {\n        &quot;x-amz-request-id&quot;: &quot;JIOFAHJNEWJDFNASD&quot;,\n        &quot;x-amz-id-2&quot;: &quot;lvTSuzcW9K77xJUIuSTn3d7B6Hz3dqw4KNd8Fc3tsMiA8g9P+B+9JoBKkUZC0aSB1Xm/7US7i/fHSfBPfuiZSgEwUumlYpaL&quot;\n      },\n      &quot;s3&quot;: {\n        &quot;s3SchemaVersion&quot;: &quot;1.0&quot;,\n        &quot;configurationId&quot;: &quot;demo-s3-to-sqs&quot;,\n        &quot;bucket&quot;: {\n          &quot;name&quot;: &quot;upload-demo-123123123&quot;,\n          &quot;ownerIdentity&quot;: {\n            &quot;principalId&quot;: &quot;ASJKDHNASDJKLASD&quot;\n          },\n          &quot;arn&quot;: &quot;arn:aws:s3:::upload-demo-42342312&quot;\n        },\n        &quot;object&quot;: {\n          &quot;key&quot;: &quot;123123/mydocument.pdf&quot;,\n          &quot;size&quot;: 11977091,\n          &quot;eTag&quot;: &quot;cf8580c55a4babf566976531bfd467d8&quot;,\n          &quot;sequencer&quot;: &quot;0066222ECC27CC73BA&quot;\n        }\n      }\n    }\n  ]\n}\n</code></pre>\n"
  },
  "answers": [],
  "question_comments": [],
  "answer_comments": {}
}