{
  "question": {
    "tags": [
      "java",
      "xml",
      "java-17",
      "jackson-dataformat-xml"
    ],
    "owner": {
      "account_id": 83131,
      "reputation": 9085,
      "user_id": 233286,
      "user_type": "registered",
      "accept_rate": 73,
      "profile_image": "https://i.sstatic.net/0ivuN.jpg?s=256",
      "display_name": "ilhan",
      "link": "https://stackoverflow.com/users/233286/ilhan"
    },
    "is_answered": true,
    "view_count": 72,
    "accepted_answer_id": 78712417,
    "answer_count": 1,
    "score": -1,
    "last_activity_date": 1722887672,
    "creation_date": 1720194812,
    "last_edit_date": 1722887672,
    "question_id": 78712351,
    "content_license": "CC BY-SA 4.0",
    "link": "https://stackoverflow.com/questions/78712351/xmlmapper-cannot-read-an-xml-content",
    "title": "XmlMapper cannot read an XML content",
    "body": "<p>I am trying to read XML content but it gives me the following error:</p>\n<blockquote>\n<p>Unrecognized field &quot;Blob&quot; (class com.example.blobstorage.dto.Blobs), not marked as ignorable (one known property: &quot;list&quot;])</p>\n</blockquote>\n<p>The XML is:</p>\n<pre><code>&lt;?xml version=&quot;1.0&quot; encoding=&quot;utf-8&quot;?&gt;\n&lt;EnumerationResults ServiceEndpoint=&quot;https://test.blob.core.windows.net/&quot; ContainerName=&quot;publicfiles&quot;&gt;\n    &lt;Blobs&gt;\n        &lt;Blob&gt;\n            &lt;Name&gt;mainfolder/test_files/test1.pdf&lt;/Name&gt;\n            &lt;Properties&gt;\n                &lt;Creation-Time&gt;Wed, 28 Feb 2024 09:28:38 GMT&lt;/Creation-Time&gt;\n                &lt;Last-Modified&gt;Wed, 28 Feb 2024 09:28:38 GMT&lt;/Last-Modified&gt;\n                &lt;Etag&gt;0x8DC383FA5196A4E&lt;/Etag&gt;\n                &lt;Content-Length&gt;187394&lt;/Content-Length&gt;\n                &lt;Content-Type&gt;application/pdf&lt;/Content-Type&gt;\n                &lt;Content-Encoding /&gt;\n                &lt;Content-Language /&gt;\n                &lt;Content-CRC64 /&gt;\n                &lt;Content-MD5&gt;HQWmDd6EBngY05LPdwQv9A==&lt;/Content-MD5&gt;\n                &lt;Cache-Control /&gt;\n                &lt;Content-Disposition /&gt;\n                &lt;BlobType&gt;BlockBlob&lt;/BlobType&gt;\n                &lt;AccessTier&gt;Hot&lt;/AccessTier&gt;\n                &lt;AccessTierInferred&gt;true&lt;/AccessTierInferred&gt;\n                &lt;LeaseStatus&gt;unlocked&lt;/LeaseStatus&gt;\n                &lt;LeaseState&gt;available&lt;/LeaseState&gt;\n                &lt;ServerEncrypted&gt;true&lt;/ServerEncrypted&gt;\n            &lt;/Properties&gt;\n            &lt;OrMetadata /&gt;\n        &lt;/Blob&gt;\n        &lt;Blob&gt;\n            &lt;Name&gt;mainfolder/test_files/test2.pdf&lt;/Name&gt;\n            &lt;Properties&gt;\n                &lt;Creation-Time&gt;Wed, 28 Feb 2024 09:28:38 GMT&lt;/Creation-Time&gt;\n                &lt;Last-Modified&gt;Wed, 28 Feb 2024 09:28:38 GMT&lt;/Last-Modified&gt;\n                &lt;Etag&gt;0x8DC383FA5191C39&lt;/Etag&gt;\n                &lt;Content-Length&gt;177902&lt;/Content-Length&gt;\n                &lt;Content-Type&gt;application/pdf&lt;/Content-Type&gt;\n                &lt;Content-Encoding /&gt;\n                &lt;Content-Language /&gt;\n                &lt;Content-CRC64 /&gt;\n                &lt;Content-MD5&gt;Z2nVrakvUEHHFuhnAk/bpg==&lt;/Content-MD5&gt;\n                &lt;Cache-Control /&gt;\n                &lt;Content-Disposition /&gt;\n                &lt;BlobType&gt;BlockBlob&lt;/BlobType&gt;\n                &lt;AccessTier&gt;Hot&lt;/AccessTier&gt;\n                &lt;AccessTierInferred&gt;true&lt;/AccessTierInferred&gt;\n                &lt;LeaseStatus&gt;unlocked&lt;/LeaseStatus&gt;\n                &lt;LeaseState&gt;available&lt;/LeaseState&gt;\n                &lt;ServerEncrypted&gt;true&lt;/ServerEncrypted&gt;\n            &lt;/Properties&gt;\n            &lt;OrMetadata /&gt;\n        &lt;/Blob&gt;\n    &lt;/Blobs&gt;\n    &lt;NextMarker /&gt;\n&lt;/EnumerationResults&gt;\n</code></pre>\n<p>I am trying to read it with:</p>\n<pre><code>EnumerationResults enumerationResults = xmlMapper.readValue(s, EnumerationResults.class); // s is the XML in string format.\n</code></pre>\n<p>I have the following classes:</p>\n<p>EnumerationResults.java</p>\n<pre><code>@Data\n@JsonIgnoreProperties(ignoreUnknown = true)\npublic class EnumerationResults implements Serializable {\n    public Blobs Blobs;\n}\n</code></pre>\n<p>Blobs.java</p>\n<pre><code>@Data\npublic class Blobs implements Serializable {\n    public List&lt;Blob&gt; list;\n}\n</code></pre>\n<p>Blob.java</p>\n<pre><code>@Data\n@JsonIgnoreProperties(ignoreUnknown = true)\npublic class Blob implements Serializable {\n    public String Name;\n}\n</code></pre>\n<p>What I am missing?</p>\n"
  },
  "answers": [],
  "question_comments": [],
  "answer_comments": {}
}