{
  "question": {
    "tags": [
      "java",
      "sql-server",
      "spring-boot"
    ],
    "owner": {
      "account_id": 30478536,
      "reputation": 61,
      "user_id": 23356681,
      "user_type": "registered",
      "profile_image": "https://lh3.googleusercontent.com/a/ACg8ocLGRm5kNmJEIhPAoBO1zlSjVMf_GEmb6PxZaLaCqZZn=k-s256",
      "display_name": "fneiwfwiem",
      "link": "https://stackoverflow.com/users/23356681/fneiwfwiem"
    },
    "is_answered": true,
    "view_count": 10720,
    "answer_count": 2,
    "score": 3,
    "last_activity_date": 1741847219,
    "creation_date": 1724830536,
    "last_edit_date": 1724830801,
    "question_id": 78922066,
    "content_license": "CC BY-SA 4.0",
    "link": "https://stackoverflow.com/questions/78922066/identifier-of-entity-must-be-manually-assigned-before-calling-persist",
    "title": "Identifier of entity must be manually assigned before calling &#39;persist()&#39;",
    "body": "<p>I'm encountering this error when i try to post through department entity.</p>\n<blockquote>\n<p>Servlet.service() for servlet [dispatcherServlet] in context with path [] threw exception [Request processing failed: org.springframework.orm.jpa.JpaSystemException: Identifier of entity 'com.ashville.usermanagementsystem.entity.Department' must be manually assigned before calling 'persist()'] with root cause</p>\n</blockquote>\n<blockquote>\n<p>org.hibernate.id.IdentifierGenerationException: Identifier of entity 'com.ashville.usermanagementsystem.entity.Department' must be manually assigned before calling 'persist()'</p>\n</blockquote>\n<p>this is my entity file.</p>\n<p>Department_id is a foreign key in User file.</p>\n<p>Department.java</p>\n<pre><code>package com.ashville.usermanagementsystem.entity;\nimport jakarta.persistence.*;\nimport java.util.List;\nimport org.springframework.boot.autoconfigure.domain.EntityScan;\n@Entity\n@Table(name = &quot;departments&quot;)\n@EntityScan(basePackages = &quot;com.ashville.usermanagementsystem.entity&quot;)\npublic class Department {\n    @Id\n    @GeneratedValue(strategy = GenerationType.AUTO)\n    private Integer departmentId;\n    @Column(nullable = false, unique = true)\n    private String deptName;\n    @OneToMany(mappedBy = &quot;department&quot;, cascade = CascadeType.ALL, fetch = FetchType.LAZY)\n    private List&lt;OurUsers&gt; users;\n    // Constructors\n    public Department() {}\n    public Department(String deptName) {\n        this.deptName = deptName;\n    }\n    // Getters and Setters\n    public Integer getDepartmentId() {\n        return departmentId;\n    }\n    public void setDepartmentId(Integer departmentId) {\n        this.departmentId = departmentId;\n    }\n    public String getDeptName() {\n        return deptName;\n    }\n    public void setDeptName(String deptName) {\n        this.deptName = deptName;\n    }\n    public List&lt;OurUsers&gt; getUsers() {\n        return users;\n    }\n    public void setUsers(List&lt;OurUsers&gt; users) {\n        this.users = users;\n    }\n}\n</code></pre>\n<p>Please help to resolve this.</p>\n"
  },
  "answers": [],
  "question_comments": [],
  "answer_comments": {}
}