{
  "question": {
    "tags": [
      "java",
      "gitlab",
      "gitlab-ci",
      "graalvm",
      "graalvm-native-image"
    ],
    "owner": {
      "account_id": 14482834,
      "reputation": 5478,
      "user_id": 10461625,
      "user_type": "registered",
      "profile_image": "https://i.sstatic.net/fgo5D.jpg?s=256",
      "display_name": "PatPanda",
      "link": "https://stackoverflow.com/users/10461625/patpanda"
    },
    "is_answered": true,
    "view_count": 608,
    "accepted_answer_id": 79235350,
    "answer_count": 1,
    "score": 1,
    "last_activity_date": 1732829812,
    "creation_date": 1730935258,
    "question_id": 79164580,
    "content_license": "CC BY-SA 4.0",
    "link": "https://stackoverflow.com/questions/79164580/gitlab-ci-cd-with-dockerstable-as-base-image-install-jdk-but-bin-sh-eval-li",
    "title": "Gitlab CI/CD with docker:stable as base image, install JDK but /bin/sh: eval: line 155: java: not found upon java --version",
    "body": "<p>I would like to invoke the java command as part of a Gitlab pipeline.</p>\n<p>The pipeline looks like:</p>\n<pre><code>build:\n  image: docker:stable\n  stage: build\n  script:\n    - wget https://download.oracle.com/graalvm/23/latest/graalvm-jdk-23_linux-x64_bin.tar.gz\n    - tar -xvf graalvm-jdk-23_linux-x64_bin.tar.gz\n    - mv graalvm-jdk-23.0.1+11.1 /opt/\n    - JAVA_HOME='/opt/graalvm-jdk-23.0.1+11.1'\n    - PATH=&quot;$JAVA_HOME/bin:$PATH&quot;\n    - echo $PATH\n    - export PATH\n    - java --version\n# // later here will download maven, compile a graalvm native image, and docker push it\n  variables:\n    DOCKER_HOST: tcp://docker:2376\n    DOCKER_TLS_CERTDIR: &quot;/certs&quot;\n    DOCKER_TLS_VERIFY: 1\n    DOCKER_CERT_PATH: &quot;$DOCKER_TLS_CERTDIR/client&quot;\n  services:\n    - docker:dind\n\n</code></pre>\n<p>However, when trying to execute the java command, I am getting: <code>/bin/sh: eval: line 155: java: not found</code></p>\n<p>I tried moving the folder, chmod 777, providing relative, absolute path, but always getting <code>/bin/sh: eval: line 155: java: not found</code>.</p>\n<p>I was expecting this step, the invocation of java --version to succeed.</p>\n<p>How to invoke java command properly?</p>\n"
  },
  "answers": [],
  "question_comments": [],
  "answer_comments": {}
}