{
  "question": {
    "tags": [
      "java",
      "spring",
      "spring-boot",
      "intellij-idea",
      "jte"
    ],
    "owner": {
      "account_id": 1189122,
      "reputation": 17456,
      "user_id": 1162409,
      "user_type": "registered",
      "accept_rate": 40,
      "profile_image": "https://i.sstatic.net/YSzYR.jpg?s=256",
      "display_name": "San Jaisy",
      "link": "https://stackoverflow.com/users/1162409/san-jaisy"
    },
    "is_answered": false,
    "view_count": 120,
    "answer_count": 0,
    "score": 1,
    "last_activity_date": 1737494653,
    "creation_date": 1731848909,
    "last_edit_date": 1732951613,
    "question_id": 79197256,
    "content_license": "CC BY-SA 4.0",
    "link": "https://stackoverflow.com/questions/79197256/java-template-engine-with-spring-boot-application-not-running-in-intellj",
    "title": "Java template engine with spring boot application not running in Intellj",
    "body": "<p>I am using the Spring authorization server with custom branding and a custom login page, with the below dependency and configuration and java template engine.</p>\n<pre><code>plugins {\n    java\n    id(&quot;org.springframework.boot&quot;) version &quot;3.3.5&quot;\n    id(&quot;io.spring.dependency-management&quot;) version &quot;1.1.6&quot;\n    id(&quot;gg.jte.gradle&quot;) version &quot;3.1.12&quot;\n}\n\ngroup = &quot;school.staff&quot;\nversion = &quot;0.0.1-SNAPSHOT&quot;\n\njava {\n    toolchain {\n        languageVersion = JavaLanguageVersion.of(21)\n    }\n}\n\nrepositories {\n    mavenCentral()\n}\n\ndependencies {\n    implementation(&quot;org.springframework.boot:spring-boot-starter-oauth2-authorization-server&quot;)\n    implementation(&quot;org.springframework.boot:spring-boot-starter-web&quot;)\n    implementation(&quot;gg.jte:jte:3.1.12&quot;)\n    implementation(&quot;gg.jte:jte-spring-boot-starter-3:3.1.12&quot;)\n    testImplementation(&quot;org.springframework.boot:spring-boot-starter-test&quot;)\n    testRuntimeOnly(&quot;org.junit.platform:junit-platform-launcher&quot;)\n}\n\njte {\n    generate()\n    binaryStaticContent = true\n}\n\ntasks.withType&lt;Test&gt; {\n    useJUnitPlatform()\n}\n</code></pre>\n<p>Below project layout</p>\n<p><a href=\"https://i.sstatic.net/IsjTQXWk.png\" rel=\"nofollow noreferrer\"><img src=\"https://i.sstatic.net/IsjTQXWk.png\" alt=\"enter image description here\" /></a></p>\n<p>Running in Intellij IDE with this configuration\n<a href=\"https://i.sstatic.net/827c0gRT.png\" rel=\"nofollow noreferrer\"><img src=\"https://i.sstatic.net/827c0gRT.png\" alt=\"enter image description here\" /></a></p>\n<p>Logs when running using Intellij IDE</p>\n<pre><code>org.springframework.security.access.AccessDeniedException: Access Denied\n    at org.springframework.security.web.access.intercept.AuthorizationFilter.doFilter(AuthorizationFilter.java:98) ~[spring-security-web-6.3.4.jar:6.3.4]\n    at org.springframework.security.web.FilterChainProxy$VirtualFilterChain.doFilter(FilterChainProxy.java:374) ~[spring-security-web-6.3.4.jar:6.3.4]\n    at org.springframework.security.web.access.ExceptionTranslationFilter.doFilter(ExceptionTranslationFilter.java:126) ~[spring-security-web-6.3.4.jar:6.3.4]\n    at org.springframework.security.web.access.ExceptionTranslationFilter.doFilter(ExceptionTranslationFilter.java:120) ~[spring-security-web-6.3.4.jar:6.3.4]\n    at org.springframework.security.web.FilterChainProxy$VirtualFilterChain.doFilter(FilterChainProxy.java:374) ~[spring-security-web-6.3.4.jar:6.3.4]\n    at org.springframework.security.web.authentication.AnonymousAuthenticationFilter.doFilter(AnonymousAuthenticationFilter.java:100) ~[spring-security-web-6.3.4.jar:6.3.4]\n    at org.springframework.security.web.FilterChainProxy$VirtualFilterChain.doFilter(FilterChainProxy.java:374) ~[spring-security-web-6.3.4.jar:6.3.4]\n    at org.springframework.security.web.servletapi.SecurityContextHolderAwareRequestFilter.doFilter(SecurityContextHolderAwareRequestFilter.java:179) ~[spring-security-web-6.3.4.jar:6.3.4]\n    at org.springframework.security.web.FilterChainProxy$VirtualFilterChain.doFilter(FilterChainProxy.java:374) ~[spring-security-web-6.3.4.jar:6.3.4]\n    at org.springframework.security.web.savedrequest.RequestCacheAwareFilter.doFilter(RequestCacheAwareFilter.java:63) ~[spring-security-web-6.3.4.jar:6.3.4]\n    at org.springframework.security.web.FilterChainProxy$VirtualFilterChain.doFilter(FilterChainProxy.java:374) ~[spring-security-web-6.3.4.jar:6.3.4]\n</code></pre>\n<p>However the code and project works perfectly fine with <code>./gradlew bootrun</code> or from any other IDE like <code>VScode</code> or <code>Fleet</code></p>\n<p>This is the issue from the IDE, not sure what is happening.</p>\n"
  },
  "answers": [],
  "question_comments": [],
  "answer_comments": {}
}