{
  "question": {
    "tags": [
      "java",
      "zgc"
    ],
    "owner": {
      "account_id": 13319128,
      "reputation": 1,
      "user_id": 9614463,
      "user_type": "registered",
      "profile_image": "https://www.gravatar.com/avatar/a9d5f73f1bae438121f67c2f049eb2e6?s=256&d=identicon&r=PG&f=y&so-version=2",
      "display_name": "zhuduohui",
      "link": "https://stackoverflow.com/users/9614463/zhuduohui"
    },
    "is_answered": false,
    "view_count": 58,
    "answer_count": 1,
    "score": 0,
    "last_activity_date": 1740221539,
    "creation_date": 1739278665,
    "question_id": 79430048,
    "content_license": "CC BY-SA 4.0",
    "link": "https://stackoverflow.com/questions/79430048/some-information-in-zgc-log",
    "title": "Some information in zgc log",
    "body": "<p>There are some debug info in our gc log.</p>\n<pre><code>[2025-02-11T10:23:12.379+0800][31569][info   ][safepoint   ] Safepoint &quot;ZMarkStart&quot;, Time since last: 408281252 ns, Reaching safepoint: 164391 ns, Cleanup: 5919 ns, At safepoint: 88609 ns, Total: 258919 ns \n[2025-02-11T10:23:13.768+0800][31935][debug  ][safepoint   ] ... found polling page loop exception at pc = 0x00007fdfed5b00ab, stub =0x00007fdfec845300 \n[2025-02-11T10:23:13.772+0800][31741][debug  ][safepoint   ] ... found polling page loop exception at pc = 0x00007fdfed15a359, stub =0x00007fdfec845300 \n[2025-02-11T10:23:13.775+0800][31741][debug  ][safepoint   ] ... found polling page loop exception at pc = 0x00007fdfed50490c, stub =0x00007fdfec845300 \n[2025-02-11T10:23:13.776+0800][31741][debug  ][safepoint   ] ... found polling page loop exception at pc = 0x00007fdfed502bcd, stub =0x00007fdfec845300 \n[2025-02-11T10:23:13.777+0800][31741][debug  ][safepoint   ] ... found polling page loop exception at pc = 0x00007fdfed0f4411, stub =0x00007fdfec845300 \n[2025-02-11T10:23:13.779+0800][32217][debug  ][safepoint   ] ... found polling page loop exception at pc = 0x00007fdfed34aae4, stub =0x00007fdfec845300 \n[2025-02-11T10:23:13.779+0800][32371][debug  ][safepoint   ] ... found polling page loop exception at pc = 0x00007fdfed2405de, stub =0x00007fdfec845300 \n[2025-02-11T10:23:13.781+0800][31741][debug  ][safepoint   ] ... found polling page loop exception at pc = 0x00007fdfed502bcd, stub =0x00007fdfec845300 \n[2025-02-11T10:23:13.781+0800][32228][debug  ][safepoint   ] ... found polling page loop exception at pc = 0x00007fdfed69a73b, stub =0x00007fdfec845300 \n[2025-02-11T10:23:13.782+0800][31545][info   ][gc,phases   ] GC(28) Concurrent Mark 1402.808ms\n</code></pre>\n<p>JVM parameters:</p>\n<pre><code>-Xms30G -Xmx30G -Xmn20g -server -Xss256K -XX:SurvivorRatio=8 -XX:-OmitStackTraceInFastThrow -XX:MaxDirectMemorySize=256G -DPreloadBufferPool.MaxMemory=70% -Dio.netty.maxDirectMemory=10474836480 -DPreloadBufferPool.WritePageExtraWeightMs=86400000 -XX:+UseZGC  -XX:+PrintGCDetails --add-opens=java.base/java.util=ALL-UNNAMED --add-opens=java.base/java.lang=ALL-UNNAMED --add-opens=java.base/java.util.concurrent.atomic=ALL-UNNAMED --add-opens=java.base/java.nio=ALL-UNNAMED --add-opens=java.base/jdk.internal.ref=ALL-UNNAMED --add-opens=java.base/jdk.internal.misc=ALL-UNNAMED -Xlog:safepoint=trace,classhisto*=trace,age*=info,gc*=info:file=/export/Logs/jmq4-server/gc-%t.log:time,level,tid,tags:filesize=500M -XX:ZAllocationSpikeTolerance=3 -XX:ZCollectionInterval=60 -XX:+UnlockDiagnosticVMOptions -XX:+LogVMOutput -XX:-ZProactive -XX:MaxMetaspaceSize=10G -DasmEnable=false\n</code></pre>\n<p>Does this log have any impact?</p>\n<p>I tried modify the gc parameters, these logs still exist.</p>\n"
  },
  "answers": [],
  "question_comments": [],
  "answer_comments": {}
}